xia_logger_gcp/__init__.py
xia_logger_gcp/logger.cp310-win_amd64.pyd
xia_logger_gcp-0.1.5.dist-info/LICENSE.txt
xia_logger_gcp-0.1.5.dist-info/METADATA
xia_logger_gcp-0.1.5.dist-info/WHEEL
xia_logger_gcp-0.1.5.dist-info/top_level.txt
xia_logger_gcp-0.1.5.dist-info/RECORD
