Metadata-Version: 2.1
Name: xia-logger-gcp
Version: 0.1.5
Summary: UNKNOWN
Home-page: https://develop.x-i-a.com/docs/xia-logger-gcp/0.1.5/index.html
Author: X-I-A
Author-email: admin@x-i-a.com
License: UNKNOWN
Platform: UNKNOWN
Requires-Python: >=3.9
License-File: LICENSE.txt
Requires-Dist: google-cloud-logging
Requires-Dist: xia-logger
